fliswarm/__init__.py
fliswarm/__main__.py
fliswarm/actor.py
fliswarm/commands.py
fliswarm/device.py
fliswarm/etc/fliswarm.yaml
fliswarm/node.py
fliswarm/tools.py
sdss_fliswarm-0.6.0.dist-info/WHEEL
sdss_fliswarm-0.6.0.dist-info/entry_points.txt
sdss_fliswarm-0.6.0.dist-info/METADATA
sdss_fliswarm-0.6.0.dist-info/RECORD
