Metadata-Version: 2.4
Name: sdss-fliswarm
Version: 0.6.0
Summary: A tool to create and manage Docker instances of flicamera
Author: José Sánchez-Gallego
Author-email: José Sánchez-Gallego <gallegoj@uw.edu>
License-Expression: BSD-3-Clause
Requires-Dist: sdsstools>=1.9.1
Requires-Dist: click>=8.0.0,<8.2.0
Requires-Dist: docker>=5.0.0
Requires-Dist: sdss-clu>=2.0.0
Requires-Dist: click-default-group>=1.2.2
Requires-Dist: numpy<2.0.0
Requires-Python: >=3.10, <4
